{"cameraMode":{"drawMode":0,"name":"Shaded","section":"Shading Mode"},"sceneLighting":true,"audioPlay":false,"sceneViewState":{"m_AlwaysRefresh":false,"showFog":true,"showSkybox":true,"showFlares":true,"showImageEffects":true,"showParticleSystems":true,"showVisualEffectGraphs":true,"m_FxEnabled":true},"in2DMode":false,"pivot":{"x":-0.6030755639076233,"y":-10.48816967010498,"z":10.765329360961914},"rotation":{"x":-0.29860958456993105,"y":-0.02090335264801979,"z":0.006544797215610743,"w":-0.9541241526603699},"size":21.559831619262697,"orthographic":false}